taskHandler/__init__.py
taskHandler/main.py
taskHandler-0.1.1.dist-info/LICENCE
taskHandler-0.1.1.dist-info/METADATA
taskHandler-0.1.1.dist-info/WHEEL
taskHandler-0.1.1.dist-info/top_level.txt
taskHandler-0.1.1.dist-info/RECORD
