Metadata-Version: 2.1
Name: taskHandler
Version: 0.1.1
Summary: taskHandker pakage will distribute all file present in give directory
Home-page: https://github.com/vardhannegi/taskHandler
Author: vardhan negi
Author-email: vardhan.negi@gmail.com
License: MIT 
Classifier: Intended Audience :: Science/Research
Classifier: License :: OSI Approved :: MIT License
Classifier: Operating System :: POSIX :: Linux
Requires-Python: >=3.5
License-File: LICENCE
Requires-Dist: os
Requires-Dist: pwd
